run.py
iquery-0.5.0.dist-info/top_level.txt
iquery-0.5.0.dist-info/RECORD
iquery-0.5.0.dist-info/entry_points.txt
iquery-0.5.0.dist-info/METADATA
iquery-0.5.0.dist-info/DESCRIPTION.rst
iquery-0.5.0.dist-info/WHEEL
iquery-0.5.0.dist-info/metadata.json
iquery/core.py
iquery/movies.py
iquery/utils.py
iquery/trains.py
iquery/lyrics.py
iquery/showes.py
iquery/__init__.py
iquery/hospitals.py
iquery/lottery.py
iquery/datas/stations.dat
iquery/datas/cities.dat
